mohou/__init__.py
mohou/asset.py
mohou/constant.py
mohou/encoder.py
mohou/encoding_rule.py
mohou/file.py
mohou/image_randomizer.py
mohou/propagator.py
mohou/py.typed
mohou/script_utils.py
mohou/setting.py
mohou/trainer.py
mohou/types.py
mohou/utils.py
mohou/dataset/__init__.py
mohou/dataset/autoencoder_dataset.py
mohou/dataset/chimera_dataset.py
mohou/dataset/sequence_dataset.py
mohou/model/__init__.py
mohou/model/autoencoder.py
mohou/model/chimera.py
mohou/model/common.py
mohou/model/experimental.py
mohou/model/lstm.py
mohou/model/third_party/__init__.py
mohou/model/third_party/variational_lstm.py
mohou/script/__init__.py
mohou/script/train_autoencoder.py
mohou/script/train_chimera.py
mohou/script/train_control_model.py
mohou/script/train_lstm.py
mohou/script/train_pblstm.py
mohou/script/visualize_autoencoder_result.py
mohou/script/visualize_lstm_result.py
mohou/script/visualize_train_history.py
mohou-0.5.11.dist-info/LICENSE
mohou-0.5.11.dist-info/METADATA
mohou-0.5.11.dist-info/WHEEL
mohou-0.5.11.dist-info/top_level.txt
mohou-0.5.11.dist-info/RECORD
