Metadata-Version: 2.1
Name: mohou
Version: 0.5.11
Summary: Visuomotor imitation learning framework
Home-page: https://github.com/HiroIshida/mohou
Author: Hirokazu Ishida
Author-email: h-ishida@jsk.imi.i.u-tokyo.ac.jp
License: MIT
Classifier: Development Status :: 5 - Production/Stable
Classifier: Intended Audience :: Developers
Classifier: Natural Language :: English
Classifier: License :: OSI Approved :: MIT License
Classifier: Programming Language :: Python :: 3.8
License-File: LICENSE
Requires-Dist: natsort
Requires-Dist: numpy
Requires-Dist: psutil
Requires-Dist: scikit-learn
Requires-Dist: torch
Requires-Dist: torchvision
Requires-Dist: tqdm
Requires-Dist: matplotlib
Requires-Dist: albumentations
Requires-Dist: moviepy
Requires-Dist: PyYAML >=5.1
Requires-Dist: types-PyYAML
Requires-Dist: gdown
Requires-Dist: opencv-python-headless <4.3.0 ; python_version < "3.7"
Requires-Dist: imageio ==2.15.0 ; python_version < "3.7"
Requires-Dist: opencv-python-headless ; python_version >= "3.8"
Provides-Extra: all
Requires-Dist: pybullet ; extra == 'all'
Requires-Dist: tinyfk <0.6 ; extra == 'all'
